harvest/__init__.py
harvest/harvest.py
harvest/metadata.py
python_harvest_redux-4.0.0.dist-info/AUTHORS
python_harvest_redux-4.0.0.dist-info/LICENSE
python_harvest_redux-4.0.0.dist-info/METADATA
python_harvest_redux-4.0.0.dist-info/WHEEL
python_harvest_redux-4.0.0.dist-info/top_level.txt
python_harvest_redux-4.0.0.dist-info/zip-safe
python_harvest_redux-4.0.0.dist-info/RECORD
