Metadata-Version: 2.1
Name: python-harvest-redux
Version: 4.0.0
Summary: Harvest API client
Home-page: https://github.com/lionheart/python-harvest
Author: Alex Goretoy
Author-email: dan@lionheartsw.com
License: Apache 2.0
Keywords: harvestapp timetracking api
Platform: UNKNOWN
Classifier: Development Status :: 5 - Production/Stable
Classifier: Environment :: Console
Classifier: Intended Audience :: Developers
Classifier: Natural Language :: English
Classifier: Operating System :: POSIX :: Linux
Classifier: Programming Language :: Python :: 2.7
Classifier: Programming Language :: Python :: 3.5
Classifier: Programming Language :: Python :: 3.6
Classifier: Topic :: Software Development :: Libraries
Classifier: Topic :: Utilities
Classifier: License :: OSI Approved :: Apache Software License
Requires-Dist: requests
Requires-Dist: requests-oauthlib
